{
  "CharacterName": "이나비",
  "CharacterWikiURL": "https://namu.wiki/w/%EC%9D%B4%EB%82%98%EB%B9%84",
  "AvailableClass": {
    "0": {
      "Name": "ベース (Alpha version)",
      "Cover": "../assets/images/Nabi_Base.png"
    },
    "1": {
      "Name": "昇級 (Alpha version)",
      "Cover": "../assets/images/Nabi_Base.png",
      "RequiredLevel": 57
    },
    "2": {
      "Name": "デザイア覚醒 (Alpha version)",
      "Cover": "../assets/images/Nabi_Desire.png",
      "RequiredLevel": 65
    }
  },
  "Skills": {
    "HitandRun": {
      "Name": "히트 앤 런",
      "DefaultLevel": 1,
      "ID": 1,
      "Icon": "../assets/SkillIcons/Nabi/Icon_RoyarRifle_Skill_HitandRun.png",
      "Levels": {
        "0": {
          "Description": "전방에 소총을 발사하여 뒤로 빠르게 이동하고 이동 중 잠시 무적상태가 되며 폭심지를 2개 설치합니다.\n이동 후 4발까지 권총 사격을 할 수 있으며 권총 사격은 얇은 상처 디버프를 남깁니다.\n얇은 상처는 샷건 타격을 받으면 폭발하여 추가피해를 줍니다.\n소총 및 권총 사격 시 근접해 있는 적을 넉백 시킵니다.",
          "Effect": "",
          "RequiredLevel": 0,
          "RequiredSP": 0,
          "Preview": {
            "Video": "../assets/SkillPreviews/Nabi/B_Skill_HitandRun.{{auto}}"
          }
        },
        "1": {
          "Effect": "[스킬 정보: 소총 사격]\n피해량: [101%]\n슈퍼아머 파괴량: [110%]\n\n[스킬 정보: 권총 사격]\n타격당 피해량: [101%]\n타격당 슈퍼아머 파괴량: [110%]\n디버프: 얇은 상처\n디버프 효과: 중첩당 샷건 타격당 피해량의 0.4배 추가피해(최대 5중첩)\n\n[스킬 정보: 일반]\nSG 소모량: [30]\n재사용 대기 시간: [15초]",
          "RequiredLevel": 0,
          "RequiredSP": 0
        },
        "2": {
          "Effect": "[스킬 정보: 소총 사격]\n피해량: [112%]\n슈퍼아머 파괴량: [121%]\n\n[스킬 정보: 권총 사격]\n타격당 피해량: [112%]\n타격당 슈퍼아머 파괴량: [121%]\n디버프: 얇은 상처\n디버프 효과: 중첩당 샷건 타격당 피해량의 0.4배 추가피해(최대 5중첩)\n\n[스킬 정보: 일반]\nSG 소모량: [30]\n재사용 대기 시간: [14초]",
          "RequiredLevel": 4,
          "RequiredSP": 1
        },
        "3": {
          "Effect": "[스킬 정보: 소총 사격]\n피해량: [125%]\n슈퍼아머 파괴량: [136%]\n\n[스킬 정보: 권총 사격]\n타격당 피해량: [125%]\n타격당 슈퍼아머 파괴량: [136%]\n디버프: 얇은 상처\n디버프 효과: 중첩당 샷건 타격당 피해량의 0.4배 추가피해(최대 5중첩)\n\n[스킬 정보: 일반]\nSG 소모량: [30]\n재사용 대기 시간: [13초]",
          "RequiredLevel": 7,
          "RequiredSP": 2
        },
        "4": {
          "Effect": "[스킬 정보: 소총 사격]\n피해량: [143%]\n슈퍼아머 파괴량: [155%]\n\n[스킬 정보: 권총 사격]\n타격당 피해량: [143%]\n타격당 슈퍼아머 파괴량: [155%]\n디버프: 얇은 상처\n디버프 효과: 중첩당 샷건 타격당 피해량의 0.4배 추가피해(최대 5중첩)\n\n[스킬 정보: 일반]\nSG 소모량: [30]\n재사용 대기 시간: [12초]",
          "RequiredLevel": 10,
          "RequiredSP": 2
        },
        "5": {
          "Effect": "[스킬 정보: 소총 사격]\n피해량: [168%]\n슈퍼아머 파괴량: [183%]\n\n[스킬 정보: 권총 사격]\n타격당 피해량: [168%]\n타격당 슈퍼아머 파괴량: [183%]\n디버프: 얇은 상처\n디버프 효과: 중첩당 샷건 타격당 피해량의 0.4배 추가피해(최대 5중첩)\n\n[스킬 정보: 일반]\nSG 소모량: [30]\n재사용 대기 시간: [10초]",
          "RequiredLevel": 13,
          "RequiredSP": 3
        }
      },
      "Extensions": [
        "HitandRun-A",
        "HitandRun-B"
      ]
    },
    "HitandRun-A": {
      "Visible": false,
      "Name": "폭심지 추가",
      "ID": 2,
      "Icon": "../assets/SkillIcons/Nabi/Icon_RoyarRifle_Skill_HitandRun_A.png",
      "Levels": {
        "0": {
          "Description": "폭심지를 추가로 설치하며 권총사격을 할 수 없습니다.",
          "Effect": "",
          "RequiredLevel": 0,
          "RequiredSP": 0,
          "Preview": {
            "Video": "../assets/SkillPreviews/Nabi/B_Skill_HitandRun_A_03.{{auto}}"
          }
        },
        "1": {
          "Effect": "[특성 정보: 폭심지]\n폭심지 설치 수: [6개]",
          "RequiredLevel": 13,
          "RequiredSP": 1
        }
      }
    },
    "HitandRun-B": {
      "Visible": false,
      "Name": "권총 대형 탄창",
      "ID": 3,
      "Icon": "../assets/SkillIcons/Nabi/Icon_RoyarRifle_Skill_HitandRun_B.png",
      "Levels": {
        "0": {
          "Description": "권총 사격의 피해량이 증가하며 최대 발사 수 제한이 증가합니다.",
          "Effect": "",
          "RequiredLevel": 0,
          "RequiredSP": 0,
          "Preview": {
            "Video": "../assets/SkillPreviews/Nabi/B_Skill_HitandRun_B.{{auto}}"
          }
        },
        "1": {
          "Effect": "[특성 정보: 권총 사격]\n타격당 피해량: [252%]\n타격당 슈퍼아머 파괴량: [274%]\n발사 횟수: [8회]",
          "RequiredLevel": 13,
          "RequiredSP": 1
        }
      }
    },
    "BlackOut": {
      "Name": "블랙아웃",
      "DefaultLevel": 1,
      "ID": 4,
      "Icon": "../assets/SkillIcons/Nabi/Icon_RoyarRifle_Skill_BlackOut.png",
      "Levels": {
        "0": {
          "Description": "",
          "Effect": "",
          "RequiredLevel": 0,
          "RequiredSP": 0,
          "Preview": {
            "Video": "../assets/SkillPreviews/Nabi/B_Skill_BlackOut.{{auto}}"
          }
        },
        "1": {
          "Effect": "",
          "RequiredLevel": 0,
          "RequiredSP": 0
        },
        "2": {
          "Effect": "",
          "RequiredLevel": 6,
          "RequiredSP": 1
        },
        "3": {
          "Effect": "",
          "RequiredLevel": 11,
          "RequiredSP": 2
        },
        "4": {
          "Effect": "",
          "RequiredLevel": 16,
          "RequiredSP": 2
        },
        "5": {
          "Effect": "",
          "RequiredLevel": 21,
          "RequiredSP": 3
        }
      },
      "Extensions": [
        "BlackOut-A"
      ]
    },
    "BlackOut-A": {
      "Visible": false,
      "Name": "장거리 투척",
      "ID": 5,
      "Icon": "../assets/SkillIcons/Nabi/Icon_RoyarRifle_Skill_BlackOut_A.png",
      "Levels": {
        "0": {
          "Description": "",
          "Effect": "",
          "RequiredLevel": 0,
          "RequiredSP": 0,
          "Preview": {
            "Video": "../assets/SkillPreviews/Nabi/B_Skill_BlackOut_A.{{auto}}"
          }
        },
        "1": {
          "Effect": "",
          "RequiredLevel": 21,
          "RequiredSP": 1
        }
      }
    },
    "QuickReload": {
      "Name": "리로드",
      "DefaultLevel": 1,
      "ID": 6,
      "Icon": "../assets/SkillIcons/Nabi/Icon_RoyarRifle_Skill_QuickReload.png",
      "Levels": {
        "0": {
          "Description": "",
          "RequiredLevel": 0,
          "RequiredSP": 0,
          "Preview": {
            "Video": "../assets/SkillPreviews/Nabi/B_Skill_QuickReload.{{auto}}"
          }
        },
        "1": {
          "Effect": "",
          "RequiredLevel": 0,
          "RequiredSP": 0
        },
        "2": {
          "Effect": "",
          "RequiredLevel": 5,
          "RequiredSP": 1
        },
        "3": {
          "Effect": "",
          "RequiredLevel": 9,
          "RequiredSP": 2
        },
        "4": {
          "Effect": "",
          "RequiredLevel": 13,
          "RequiredSP": 2
        },
        "5": {
          "Effect": "",
          "RequiredLevel": 17,
          "RequiredSP": 3
        }
      },
      "Extensions": [
        "QuickReload-A",
        "QuickReload-B"
      ]
    },
    "QuickReload-A": {
      "Visible": false,
      "ID": 7,
      "Name": "플레셰트",
      "Icon": "../assets/SkillIcons/Nabi/Icon_RoyarRifle_Skill_QuickReload_A.png",
      "Levels": {
        "0": {
          "Description": "",
          "Effect": "",
          "RequiredLevel": 0,
          "RequiredSP": 0,
          "Preview": {
            "Video": "../assets/SkillPreviews/Nabi/B_Skill_QuickReload_A.{{auto}}"
          }
        },
        "1": {
          "Effect": "",
          "RequiredLevel": 17,
          "RequiredSP": 1
        },
        "2": {
          "Effect": "",
          "RequiredLevel": 22,
          "RequiredSP": 1
        },
        "3": {
          "Effect": "",
          "RequiredLevel": 27,
          "RequiredSP": 2
        }
      }
    },
    "QuickReload-B": {
      "Visible": false,
      "ID": 8,
      "Name": "파쇄탄",
      "Icon": "../assets/SkillIcons/Nabi/Icon_RoyarRifle_Skill_QuickReload_B.png",
      "Levels": {
        "0": {
          "Description": "",
          "Effect": "",
          "RequiredLevel": 0,
          "RequiredSP": 0,
          "Preview": {
            "Video": "../assets/SkillPreviews/Nabi/B_Skill_QuickReload_B.{{auto}}"
          }
        },
        "1": {
          "Effect": "",
          "RequiredLevel": 17,
          "RequiredSP": 1
        },
        "2": {
          "Effect": "",
          "RequiredLevel": 22,
          "RequiredSP": 1
        },
        "3": {
          "Effect": "",
          "RequiredLevel": 27,
          "RequiredSP": 2
        }
      }
    },
    "SnakingShotgun": {
      "Name": "스네이킹 샷건",
      "ID": 9,
      "Icon": "../assets/SkillIcons/Nabi/Icon_RoyarRifle_Skill_SnakingShotgun.png",
      "Levels": {
        "0": {
          "Description": "",
          "Effect": "",
          "RequiredLevel": 0,
          "RequiredSP": 0,
          "Preview": {
            "Video": "../assets/SkillPreviews/Nabi/B_Skill_SnakingShotgun.{{auto}}"
          }
        },
        "1": {
          "Effect": "",
          "RequiredLevel": 4,
          "RequiredSP": 1
        },
        "2": {
          "Effect": "",
          "RequiredLevel": 8,
          "RequiredSP": 1
        },
        "3": {
          "Effect": "",
          "RequiredLevel": 12,
          "RequiredSP": 2
        },
        "4": {
          "Effect": "",
          "RequiredLevel": 16,
          "RequiredSP": 2
        },
        "5": {
          "Effect": "",
          "RequiredLevel": 20,
          "RequiredSP": 3
        }
      }
    },
    "Acidgas": {
      "Name": "애시드 가스",
      "ID": 10,
      "Icon": "../assets/SkillIcons/Nabi/Icon_RoyarRifle_Skill_Acidgas.png",
      "Levels": {
        "0": {
          "Description": "",
          "Effect": "",
          "RequiredLevel": 0,
          "RequiredSP": 0,
          "Preview": {
            "Video": "../assets/SkillPreviews/Nabi/B_Skill_Acidgas.{{auto}}"
          }
        },
        "1": {
          "Effect": "",
          "RequiredLevel": 6,
          "RequiredSP": 1
        },
        "2": {
          "Effect": "",
          "RequiredLevel": 10,
          "RequiredSP": 1
        },
        "3": {
          "Effect": "",
          "RequiredLevel": 14,
          "RequiredSP": 2
        },
        "4": {
          "Effect": "",
          "RequiredLevel": 18,
          "RequiredSP": 2
        },
        "5": {
          "Effect": "",
          "RequiredLevel": 22,
          "RequiredSP": 3
        }
      },
      "Extensions": [
        "Acidgas-A"
      ]
    },
    "Acidgas-A": {
      "Visible": false,
      "Name": "폭심지 지정",
      "ID": 11,
      "Icon": "../assets/SkillIcons/Nabi/Icon_RoyarRifle_Skill_Acidgas_A.png",
      "Levels": {
        "0": {
          "Description": "",
          "Effect": "",
          "RequiredLevel": 0,
          "RequiredSP": 0,
          "Preview": {
            "Video": "../assets/SkillPreviews/Nabi/B_Skill_Acidgas_A_01.{{auto}}"
          }
        },
        "1": {
          "Effect": "",
          "RequiredLevel": 22,
          "RequiredSP": 1
        },
        "2": {
          "Effect": "",
          "RequiredLevel": 27,
          "RequiredSP": 1,
          "Preview": {
            "Video": "../assets/SkillPreviews/Nabi/B_Skill_Acidgas_A_02.{{auto}}"
          }
        },
        "3": {
          "Effect": "",
          "RequiredLevel": 32,
          "RequiredSP": 2,
          "Preview": {
            "Video": "../assets/SkillPreviews/Nabi/B_Skill_Acidgas_A_03.{{auto}}"
          }
        }
      }
    },
    "BustDriver": {
      "Name": "버스트 드라이버",
      "ID": 12,
      "Icon": "../assets/SkillIcons/Nabi/Icon_RoyarRifle_Skill_BustDriver.png",
      "Levels": {
        "0": {
          "Description": "",
          "Effect": "",
          "RequiredLevel": 0,
          "RequiredSP": 0,
          "Preview": {
            "Video": "../assets/SkillPreviews/Nabi/B_Skill_BustDriver.{{auto}}"
          }
        },
        "1": {
          "Effect": "",
          "RequiredLevel": 8,
          "RequiredSP": 1
        },
        "2": {
          "Effect": "",
          "RequiredLevel": 12,
          "RequiredSP": 1
        },
        "3": {
          "Effect": "",
          "RequiredLevel": 16,
          "RequiredSP": 2
        },
        "4": {
          "Effect": "",
          "RequiredLevel": 20,
          "RequiredSP": 2
        },
        "5": {
          "Effect": "",
          "RequiredLevel": 24,
          "RequiredSP": 3
        }
      },
      "Extensions": [
        "BustDriver-A"
      ]
    },
    "FlagBomb": {
      "ID": 13,
      "Name": "프래그 봄",
      "Icon": "../assets/SkillIcons/Nabi/Icon_RoyarRifle_Skill_FlagBomb.png",
      "Levels": {
        "0": {
          "Description": "",
          "Effect": "",
          "RequiredLevel": 0,
          "RequiredSP": 0,
          "Preview": {
            "Video": "../assets/SkillPreviews/Nabi/B_Skill_FlagBomb.{{auto}}"
          }
        },
        "1": {
          "Effect": "",
          "RequiredLevel": 10,
          "RequiredSP": 1
        },
        "2": {
          "Effect": "",
          "RequiredLevel": 15,
          "RequiredSP": 1
        },
        "3": {
          "Effect": "",
          "RequiredLevel": 20,
          "RequiredSP": 2
        },
        "4": {
          "Effect": "",
          "RequiredLevel": 25,
          "RequiredSP": 2
        },
        "5": {
          "Effect": "",
          "RequiredLevel": 30,
          "RequiredSP": 3
        }
      },
      "Extensions": [
        "FlagBomb-A",
        "FlagBomb-B"
      ]
    },
    "FlagBomb-A": {
      "ID": 14,
      "Visible": false,
      "Name": "추가 폭발",
      "Icon": "../assets/SkillIcons/Nabi/Icon_RoyarRifle_Skill_FlagBomb_A.png",
      "Levels": {
        "0": {
          "Description": "",
          "Effect": "",
          "RequiredLevel": 0,
          "RequiredSP": 0,
          "Preview": {
            "Video": "../assets/SkillPreviews/Nabi/B_Skill_FlagBomb_A.{{auto}}"
          }
        },
        "1": {
          "Effect": "",
          "RequiredLevel": 33,
          "RequiredSP": 1
        },
        "2": {
          "Effect": "",
          "RequiredLevel": 38,
          "RequiredSP": 1
        },
        "3": {
          "Effect": "",
          "RequiredLevel": 40,
          "RequiredSP": 2
        }
      }
    },
    "FlagBomb-B": {
      "ID": 15,
      "Visible": false,
      "Name": "열압력화기",
      "Icon": "../assets/SkillIcons/Nabi/Icon_RoyarRifle_Skill_FlagBomb_B.png",
      "Levels": {
        "0": {
          "Description": "",
          "Effect": "",
          "RequiredLevel": 0,
          "RequiredSP": 0,
          "Preview": {
            "Video": "../assets/SkillPreviews/Nabi/B_Skill_FlagBomb_B.{{auto}}"
          }
        },
        "1": {
          "Effect": "",
          "RequiredLevel": 33,
          "RequiredSP": 1
        },
        "2": {
          "Effect": "",
          "RequiredLevel": 38,
          "RequiredSP": 1
        },
        "3": {
          "Effect": "",
          "RequiredLevel": 40,
          "RequiredSP": 2
        }
      }
    },    
    "HuneyBee": {
      "Name": "허니비 ",
      "ID": 16,
      "Icon": "../assets/SkillIcons/Nabi/Icon_RoyarRifle_Skill_HuneyBee.png",
      "Levels": {
        "0": {
          "Description": "",
          "Effect": "",
          "RequiredLevel": 0,
          "RequiredSP": 0,
          "Preview": {
            "Video": "../assets/SkillPreviews/Nabi/B_Skill_HoneyBee.{{auto}}"
          }
        },
        "1": {
          "Effect": "",
          "RequiredLevel": 13,
          "RequiredSP": 1
        },
        "2": {
          "Effect": "",
          "RequiredLevel": 18,
          "RequiredSP": 1
        },
        "3": {
          "Effect": "",
          "RequiredLevel": 23,
          "RequiredSP": 2
        },
        "4": {
          "Effect": "",
          "RequiredLevel": 28,
          "RequiredSP": 2
        },
        "5": {
          "Effect": "",
          "RequiredLevel": 33,
          "RequiredSP": 3
        }
      },
      "Extensions": [
        "HuneyBee-A"
      ]
    },    
    "CloseQuartersCombat": {
      "Name": "클로즈 쿼터스 컴뱃",
      "ID": 17,
      "Icon": "../assets/SkillIcons/Nabi/Icon_RoyarRifle_Skill_CloseQuartersCombat.png",
      "Levels": {
        "0": {
          "Description": "",
          "Effect": "",
          "RequiredLevel": 0,
          "RequiredSP": 0,
          "Preview": {
            "Video": "../assets/SkillPreviews/Nabi/B_Skill_CloseQuartersCombat.{{auto}}"
          }
        },
        "1": {
          "Effect": "",
          "RequiredLevel": 34,
          "RequiredSP": 1
        },
        "2": {
          "Effect": "",
          "RequiredLevel": 38,
          "RequiredSP": 1
        },
        "3": {
          "Effect": "",
          "RequiredLevel": 42,
          "RequiredSP": 2
        },
        "4": {
          "Effect": "",
          "RequiredLevel": 46,
          "RequiredSP": 2
        },
        "5": {
          "Effect": "",
          "RequiredLevel": 50,
          "RequiredSP": 3
        }
      }
    },
    "Chainsaw": {
      "Name": "체인쏘우",
      "ID": 18,
      "Icon": "../assets/SkillIcons/Nabi/Icon_RoyarRifle_Skill_Chainsaw.png",
      "Levels": {
        "0": {
          "Description": "",
          "Effect": "",
          "RequiredLevel": 0,
          "RequiredSP": 0,
          "Preview": {
            "Video": "../assets/SkillPreviews/Nabi/B_Skill_Chainsaw.{{auto}}"
          }
        },
        "1": {
          "Effect": "",
          "RequiredLevel": 21,
          "RequiredSP": 1
        },
        "2": {
          "Effect": "",
          "RequiredLevel": 26,
          "RequiredSP": 1
        },
        "3": {
          "Effect": "",
          "RequiredLevel": 31,
          "RequiredSP": 2
        },
        "4": {
          "Effect": "",
          "RequiredLevel": 36,
          "RequiredSP": 2
        },
        "5": {
          "Effect": "",
          "RequiredLevel": 41,
          "RequiredSP": 3
        }
      },
      "Extensions": [
        "Chainsaw-A",
        "Chainsaw-B"
      ]
    },
    "Chainsaw-A": {
      "Visible": false,
      "Name": "소이탄",
      "ID": 20,
      "Icon": "../assets/SkillIcons/Nabi/Icon_RoyarRifle_Skill_Chainsaw_A.png",
      "Levels": {
        "0": {
          "Description": "",
          "Effect": "",
          "RequiredLevel": 0,
          "RequiredSP": 0,
          "Preview": {
            "Video": "../assets/SkillPreviews/Nabi/B_Skill_Chainsaw_A.{{auto}}"
          }
        },
        "1": {
          "Effect": "",
          "RequiredLevel": 44,
          "RequiredSP": 1
        },
        "2": {
          "Effect": "",
          "RequiredLevel": 49,
          "RequiredSP": 1
        },
        "3": {
          "Effect": "",
          "RequiredLevel": 51,
          "RequiredSP": 2
        }
      }
    },
    "Chainsaw-B": {
      "Visible": false,
      "Name": "철갑탄",
      "ID": 20,
      "Icon": "../assets/SkillIcons/Nabi/Icon_RoyarRifle_Skill_Chainsaw_B.png",
      "Levels": {
        "0": {
          "Description": "",
          "Effect": "",
          "RequiredLevel": 0,
          "RequiredSP": 0,
          "Preview": {
            "Video": "../assets/SkillPreviews/Nabi/B_Skill_Chainsaw_B.{{auto}}"
          }
        },
        "1": {
          "Effect": "",
          "RequiredLevel": 44,
          "RequiredSP": 1
        },
        "2": {
          "Effect": "",
          "RequiredLevel": 49,
          "RequiredSP": 1
        },
        "3": {
          "Effect": "",
          "RequiredLevel": 51,
          "RequiredSP": 2
        }
      }
    },
    "GranadeLauncher": {
      "Name": "그레네이드 런처",
      "ID": 21,
      "Icon": "../assets/SkillIcons/Nabi/Icon_RoyarRifle_Skill_GranadeLauncher.png",
      "Levels": {
        "0": {
          "Description": "ソウルエナジーを放出し、バリアを付与する。",
          "Effect": "",
          "RequiredLevel": 0,
          "RequiredSP": 0,
          "Preview": {
            "Video": "../assets/SkillPreviews/Nabi/B_Skill_GranadeLauncher.{{auto}}"
          }
        },
        "1": {
          "Effect": "",
          "RequiredLevel": 28,
          "RequiredSP": 1
        },
        "2": {
          "Effect": "",
          "RequiredLevel": 32,
          "RequiredSP": 1
        },
        "3": {
          "Effect": "",
          "RequiredLevel": 38,
          "RequiredSP": 2
        },
        "4": {
          "Effect": "",
          "RequiredLevel": 42,
          "RequiredSP": 2
        },
        "5": {
          "Effect": "",
          "RequiredLevel": 48,
          "RequiredSP": 3
        }
      }
    },
    "Thunderbolt": {
      "Name": "세이브 에너지",
      "ID": 22,
      "Icon": "../assets/SkillIcons/Nabi/Icon_RoyarRifle_Skill_SaveEnergy.png",
      "Levels": {
        "0": {
          "Description": "",
          "Effect": "",
          "RequiredLevel": 0,
          "RequiredSP": 0,
          "Preview": {
            "Video": "../assets/SkillPreviews/Nabi/B_Skill_SaveEnergy.{{auto}}"
          }
        },
        "1": {
          "Effect": "",
          "RequiredLevel": 34,
          "RequiredSP": 1
        },
        "2": {
          "Effect": "",
          "RequiredLevel": 37,
          "RequiredSP": 1
        },
        "3": {
          "Effect": "",
          "RequiredLevel": 40,
          "RequiredSP": 2
        },
        "4": {
          "Effect": "",
          "RequiredLevel": 43,
          "RequiredSP": 2
        },
        "5": {
          "Effect": "",
          "RequiredLevel": 46,
          "RequiredSP": 3
        }
      },
      "Extensions": [
        "SaveEnergy-A"
      ]
    },
    "SaveEnergy-A": {
      "Visible": false,
      "Name": "추가 보급품",
      "ID": 23,
      "Icon": "../assets/SkillIcons/Nabi/Icon_RoyarRifle_Skill_SaveEnergy_A.png",
      "Levels": {
        "0": {
          "Description": "",
          "Effect": "",
          "RequiredLevel": 0,
          "RequiredSP": 0,
          "Preview": {
            "Video": "../assets/SkillPreviews/Nabi/B_Skill_SaveEnergy_A_01.{{auto}}"
          }
        },
        "1": {
          "Effect": "",
          "RequiredLevel": 46,
          "RequiredSP": 1
        },
        "2": {
          "Effect": "",
          "RequiredLevel": 50,
          "RequiredSP": 1,
          "Preview": {
            "Video": "../assets/SkillPreviews/Nabi/B_Skill_SaveEnergy_A_02.{{auto}}"
          }
        },
        "3": {
          "Effect": "",
          "RequiredLevel": 54,
          "RequiredSP": 2,
          "Preview": {
            "Video": "../assets/SkillPreviews/Nabi/B_Skill_SaveEnergy_A_03.{{auto}}"
          }
        }
      }
    },
    "LastStrike": {
      "Name": "라스트 스트라이크",
      "ID": 24,
      "Icon": "../assets/SkillIcons/Nabi/Icon_RoyarRifle_Skill_LastStrike.png",
      "Levels": {
        "0": {
          "Description": "",
          "Effect": "",
          "RequiredLevel": 0,
          "RequiredSP": 0,
          "Preview": {
            "Video": "../assets/SkillPreviews/Nabi/B_Skill_LastStrike.{{auto}}"
          }
        },
        "1": {
          "Effect": "",
          "RequiredLevel": 42,
          "RequiredSP": 1
        },
        "2": {
          "Effect": "",
          "RequiredLevel": 45,
          "RequiredSP": 1
        },
        "3": {
          "Effect": "",
          "RequiredLevel": 48,
          "RequiredSP": 2
        },
        "4": {
          "Effect": "",
          "RequiredLevel": 51,
          "RequiredSP": 2
        },
        "5": {
          "Effect": "",
          "RequiredLevel": 54,
          "RequiredSP": 3
        }
      },
      "Extensions": [
        "LastStrike-A"
      ]
    },
    "BustDriver-A": {
      "Visible": false,
      "Name": "모드 변경",
      "ID": 25,
      "RequireClass": {
        "CompareType": "atleast",
        "ClassIndex": 1
      },
      "Icon": "../assets/SkillIcons/Nabi/Icon_RoyarRifle_Skill_BustDriver_A.png",
      "Levels": {
        "0": {
          "Description": "",
          "Effect": "",
          "RequiredLevel": 0,
          "RequiredSP": 0,
          "Preview": {
            "Video": "../assets/SkillPreviews/Nabi/B_Skill_BustDriver_A.{{auto}}"
          }
        },
        "1": {
          "Effect": "",
          "RequiredLevel": 57,
          "RequiredSP": 1
        },
        "2": {
          "Effect": "",
          "RequiredLevel": 59,
          "RequiredSP": 1
        },
        "3": {
          "Effect": "",
          "RequiredLevel": 60,
          "RequiredSP": 2
        }
      }
    },
    "HuneyBee-A": {
      "Visible": false,
      "Name": "포탑",
      "ID": 26,
      "RequireClass": {
        "CompareType": "atleast",
        "ClassIndex": 1
      },
      "Icon": "../assets/SkillIcons/Nabi/Icon_RoyarRifle_Skill_HuneyBee_A.png",
      "Levels": {
        "0": {
          "Description": "",
          "Effect": "",
          "RequiredLevel": 0,
          "RequiredSP": 0,
          "Preview": {
            "Video": "../assets/SkillPreviews/Nabi/B_Skill_HoneyBee_A_01.{{auto}}"
          }
        },
        "1": {
          "Effect": "",
          "RequiredLevel": 57,
          "RequiredSP": 1
        },
        "2": {
          "Effect": "",
          "RequiredLevel": 59,
          "RequiredSP": 1,
          "Preview": {
            "Video": "../assets/SkillPreviews/Nabi/B_Skill_HoneyBee_A_02.{{auto}}"
          }        
        },
        "3": {
          "Effect": "",
          "RequiredLevel": 60,
          "RequiredSP": 2,
          "Preview": {
            "Video": "../assets/SkillPreviews/Nabi/B_Skill_HoneyBee_A_03.{{auto}}"
          }
        }
      }
    },
    "TripleSniping": {
      "Name": "트리플 스나이핑",
      "ID": 27,
      "RequireClass": {
        "CompareType": "atleast",
        "ClassIndex": 1
      },
      "Icon": "../assets/SkillIcons/Nabi/Icon_RoyarRifle_Skill_TripleSniping.png",
      "Assignable": false,
      "Levels": {
        "0": {
          "Description": "",
          "Effect": "",
          "RequiredLevel": 0,
          "RequiredSP": 0,
          "Preview": {
            "Video": "../assets/SkillPreviews/Nabi/B_Skill_TripleSniping.{{auto}}"
          }
        },
        "1": {
          "Effect": "",
          "RequiredLevel": 57,
          "RequiredSP": 1
        },
        "2": {
          "Effect": "",
          "RequiredLevel": 57,
          "RequiredSP": 1
        },
        "3": {
          "Effect": "",
          "RequiredLevel": 58,
          "RequiredSP": 2
        },
        "4": {
          "Effect": "",
          "RequiredLevel": 59,
          "RequiredSP": 2
        },
        "5": {
          "Effect": "",
          "RequiredLevel": 60,
          "RequiredSP": 3
        }
      }
    },
    "WildSnapshot": {
      "Name": "와일드 스냅샷 ",
      "ID": 28,
      "RequireClass": {
        "CompareType": "atleast",
        "ClassIndex": 1
      },
      "Icon": "../assets/SkillIcons/Nabi/Icon_RoyarRifle_Skill_WildSnapshot.png",
      "Levels": {
        "0": {
          "Description": "",
          "Effect": "",
          "RequiredLevel": 0,
          "RequiredSP": 0,
          "Preview": {
            "Video": "../assets/SkillPreviews/Nabi/B_Skill_WildSnapshot.{{auto}}"
          }
        },
        "1": {
          "Effect": "",
          "RequiredLevel": 57,
          "RequiredSP": 1
        },
        "2": {
          "Effect": "",
          "RequiredLevel": 57,
          "RequiredSP": 1
        },
        "3": {
          "Effect": "",
          "RequiredLevel": 58,
          "RequiredSP": 2
        },
        "4": {
          "Effect": "",
          "RequiredLevel": 59,
          "RequiredSP": 2
        },
        "5": {
          "Effect": "",
          "RequiredLevel": 60,
          "RequiredSP": 3
        }
      }
    },
    "Destronail": {
      "Name": "디스트로네일",
      "ID": 29,
      "Icon": "../assets/SkillIcons/Nabi/Icon_RoyarRifle_Skill_Destronail.png",
      "Levels": {
        "0": {
          "Description": "",
          "Effect": "",
          "RequiredLevel": 0,
          "RequiredSP": 0,
          "Preview": {
            "Video": "../assets/SkillPreviews/Nabi/B_Skill_Destronail.{{auto}}"
          }
        },
        "1": {
          "Effect": "",
          "RequiredLevel": 62,
          "RequiredSP": 1
        },
        "2": {
          "Effect": "",
          "RequiredLevel": 65,
          "RequiredSP": 1
        },
        "3": {
          "Effect": "",
          "RequiredLevel": 68,
          "RequiredSP": 2
        },
        "4": {
          "Effect": "",
          "RequiredLevel": 71,
          "RequiredSP": 3
        }
      }
    },
    "LastStrike-A": {
      "Visible": false,
      "Name": "후폭풍",
      "ID": 30,
      "Icon": "../assets/SkillIcons/Nabi/Icon_RoyarRifle_Skill_LastStrike_A.png",
      "Levels": {
        "0": {
          "Description": "",
          "Effect": "",
          "RequiredLevel": 0,
          "RequiredSP": 0,
          "Preview": {
            "Video": "../assets/SkillPreviews/Nabi/B_Skill_LastStrike_A.{{auto}}"
          }
        },
        "1": {
          "Effect": "",
          "RequiredLevel": 68,
          "RequiredSP": 2
        },
        "2": {
          "Effect": "",
          "RequiredLevel": 70,
          "RequiredSP": 3
        },
        "3": {
          "Effect": "",
          "RequiredLevel": 72,
          "RequiredSP": 4
        }
      }
    },
    "BasicAttackMastery": {
      "Passive": true,
      "Name": "基本攻撃マスタリー",
      "ID": 1001,
      "DefaultLevel": 1,
      "Icon": "../assets/SkillIcons/Common/Icon_Common_Skill_DefaultAttack.png",
      "Levels": {
        "0": {
          "Description": "",
          "Effect": "",
          "RequiredLevel": 0,
          "RequiredSP": 0,
          "Preview": {
            "Video": "../assets/SkillPreviews/Nabi/B_Attack_01.{{auto}}"
          }
        },
        "1": {
          "Effect": "",
          "RequiredLevel": 0,
          "RequiredSP": 0
        },
        "2": {
          "Effect": "",
          "RequiredLevel": 5,
          "RequiredSP": 1,
          "Preview": {
            "Video": "../assets/SkillPreviews/Nabi/B_Attack_01.{{auto}}"
          }
        },
        "3": {
          "Effect": "",
          "RequiredLevel": 10,
          "RequiredSP": 2,
          "Preview": {
            "Video": "../assets/SkillPreviews/Nabi/B_Attack_02.{{auto}}"
          }
        },
        "4": {
          "Effect": "",
          "RequiredLevel": 15,
          "RequiredSP": 2,
          "Preview": {
            "Video": "../assets/SkillPreviews/Nabi/B_Attack_02.{{auto}}"
          }
        },
        "5": {
          "Effect": "",
          "RequiredLevel": 20,
          "RequiredSP": 2,
          "Preview": {
            "Video": "../assets/SkillPreviews/Nabi/B_Attack_03.{{auto}}"
          }
        }
      }
    },
    "SpecialAbilityMastery": {
      "Passive": true,
      "DefaultLevel": 1,
      "ID": 1002,
      "Name": "特殊能力マスタリー",
      "Icon": "../assets/SkillIcons/Nabi/Icon_RoyarRifle_Skill_OwnAbility.png",
      "Levels": {
        "0": {
          "Description": "",
          "Effect": "",
          "RequiredLevel": 0,
          "RequiredSP": 0,
          "Preview": {
            "Video": "../assets/SkillPreviews/Nabi/B_S_Attack_N.{{auto}}"
          }
        },
        "1": {
          "Effect": "",
          "RequiredLevel": 0,
          "RequiredSP": 0
        },
        "2": {
          "Effect": "",
          "RequiredLevel": 15,
          "RequiredSP": 1
        },
        "3": {
          "Effect": "",
          "RequiredLevel": 30,
          "RequiredSP": 2
        }
      }
    },
    "EmergencyEvasion": {
      "Passive": true,
      "Name": "緊急回避",
      "ID": 1003,
      "DefaultLevel": 1,
      "Icon": "../assets/SkillIcons/Common/Icon_Common_Skill_Evasion.png",
      "Levels": {
        "0": {
          "Description": "指定した方向に素早く移動する。\n緊急回避中はダメージを受けない。",
          "Effect": "",
          "RequiredLevel": 0,
          "RequiredSP": 0,
          "Preview": {
            "Video": "../assets/SkillPreviews/Nabi/B_Evade_F.{{auto}}"
          }
        },
        "1": {
          "Effect": "スタミナ消費量：[20]",
          "RequiredLevel": 0,
          "RequiredSP": 0
        }
      }
    },
    "Welter": {
      "Passive": true,
      "Name": "回転起床",
      "ID": 1004,
      "DefaultLevel": 1,
      "Icon": "../assets/SkillIcons/Common/Icon_Common_Skill_Welter.png",
      "Levels": {
        "0": {
          "Description": "ダウン時、指定した方向に素早く回転しながら起き上がる。\n回転起床中はダメージを受けない。",
          "Effect": "",
          "RequiredLevel": 0,
          "RequiredSP": 0,
          "Preview": {
            "Video": "../assets/SkillPreviews/Nabi/B_Roll_F.{{auto}}"
          }
        },
        "1": {
          "Effect": "スタミナ消費量：[25]",
          "RequiredLevel": 0,
          "RequiredSP": 0
        },
        "2": {
          "Effect": "スタミナ消費量：[15]",
          "RequiredLevel": 17,
          "RequiredSP": 1
        },
        "3": {
          "Effect": "スタミナ消費量：[15]\n少し早く回転起床ができる。 ",
          "RequiredLevel": 34,
          "RequiredSP": 2
        }
      }
    },
    "Dash": {
      "Passive": true,
      "Name": "ダッシュ",
      "DefaultLevel": 1,
      "ID": 1005,
      "Icon": "../assets/SkillIcons/Common/Icon_Common_Skill_Dash.png",
      "Levels": {
        "0": {
          "Description": "前方に素早くダッシュする。",
          "Effect": "",
          "RequiredLevel": 0,
          "RequiredSP": 0,
          "Preview": {
            "Video": "../assets/SkillPreviews/Nabi/B_Run_F.{{auto}}"
          }
        },
        "1": {
          "Effect": "",
          "RequiredLevel": 0,
          "RequiredSP": 0
        },
        "2": {
          "Effect": "ダッシュの速度が上昇する。",
          "RequiredLevel": 25,
          "RequiredSP": 2
        }
      }
    },
    "RisingAttack": {
      "Passive": true,
      "Name": "起床攻撃",
      "ID": 1006,
      "DefaultLevel": 1,
      "Icon": "../assets/SkillIcons/Common/Icon_Common_Skill_RiseAttack.png",
      "Levels": {
        "0": {
          "Description": "ダウン時、周辺の敵を攻撃しながら起き上がる。",
          "Effect": "",
          "RequiredLevel": 0,
          "RequiredSP": 0,
          "Preview": {
            "Video": "../assets/SkillPreviews/Nabi/B_Rise_Attack.{{auto}}"
          }
        },
        "1": {
          "Effect": "ダメージ量：[100%]\nスタミナ消費量：[30]\nクールタイム：[15秒]\nスキル使用後3秒間、無敵状態になる。",
          "RequiredLevel": 0,
          "RequiredSP": 0
        },
        "2": {
          "Effect": "ダメージ量：[100%]\nスタミナ消費量：[20]\nクールタイム：[15秒]\nスキル使用後3秒間、無敵状態になる。",
          "RequiredLevel": 18,
          "RequiredSP": 1
        },
        "3": {
          "Effect": "ダメージ量：[100%]\nスタミナ消費量：[20]\nクールタイム：[15秒]\nスキル使用後5秒間、無敵状態になる。",
          "RequiredLevel": 36,
          "RequiredSP": 2
        }
      }
    },
    "DashAttack": {
      "Passive": true,
      "Name": "ダッシュアタック",
      "DefaultLevel": 1,
      "ID": 1007,
      "Icon": "../assets/SkillIcons/Common/Icon_Common_Skill_DashAttack.png",
      "Levels": {
        "0": {
          "Description": "달리던 도중 전방을 향해 헥토파스칼킥을 사용합니다.",
          "Effect": "",
          "RequiredLevel": 0,
          "RequiredSP": 0,
          "Preview": {
            "Video": "../assets/SkillPreviews/Nabi/B_N_Attack_Dash.{{auto}}"
          }
        },
        "1": {
          "Effect": "피해량: [116%]\n슈퍼아머 파괴량: [46%]",
          "RequiredLevel": 0,
          "RequiredSP": 0
        }
      }
    },
    "SpecialEvasion": {
      "Passive": true,
      "Name": "特殊回避",
      "ID": 1008,
      "Icon": "../assets/SkillIcons/Common/Icon_Common_Skill_EvasionAttack.png",
      "Levels": {
        "0": {
          "Description": "敵から攻撃を受けている最中に素早く移動する。\n特殊回避中はダメージを受けない。",
          "Effect": "",
          "RequiredLevel": 0,
          "RequiredSP": 0,
          "Preview": {
            "Video": "../assets/SkillPreviews/Nabi/B_Special_Evade_F.{{auto}}"
          }
        },
        "1": {
          "Effect": "スタミナ消費量：[40]\nクールタイム：[30秒]",
          "RequiredLevel": 4,
          "RequiredSP": 1
        },
        "2": {
          "Effect": "スタミナ消費量：[40]\nクールタイム：[25秒]",
          "RequiredLevel": 21,
          "RequiredSP": 1
        },
        "3": {
          "Effect": "スタミナ消費量：[40]\nクールタイム：[20秒]",
          "RequiredLevel": 38,
          "RequiredSP": 2
        }
      }
    },
    "SpecialDashAttack": {
      "Passive": true,
      "Name": "特殊ダッシュアタック",
      "ID": 1009,
      "Icon": "../assets/SkillIcons/Common/Icon_Common_Skill_DashSmashAttack.png",
      "Levels": {
        "0": {
          "Description": "달리는 자세를 낮춘 상태에서 앞으로 미끄러지며 지나온 자리에 폭심지를 3개 설치합니다.",
          "Effect": "",
          "RequiredLevel": 0,
          "RequiredSP": 0,
          "Preview": {
            "Video": "../assets/SkillPreviews/Nabi/B_S_Attack_N_Dash.{{auto}}"
          }
        },
        "1": {
          "Effect": "폭심지 설치 수: [3개]\n스태미나 소모량: [20]\n재사용 대기시간: [6초]",
          "RequiredLevel": 13,
          "RequiredSP": 1
        }
      }
    },
    "StaminaMastery": {
      "Passive": true,
      "Name": "スタミナマスタリー",
      "ID": 1010,
      "Icon": "../assets/SkillIcons/Common/Icon_Common_Skill_StaminaMastery.png",
      "Levels": {
        "0": {
          "Description": "スタミナ回復量が増加する。",
          "Effect": "",
          "RequiredLevel": 0,
          "RequiredSP": 0
        },
        "1": {
          "Effect": "スタミナ回復量[10%]増加",
          "RequiredLevel": 10,
          "RequiredSP": 1
        },
        "2": {
          "Effect": "スタミナ回復量[20%]増加",
          "RequiredLevel": 15,
          "RequiredSP": 1
        },
        "3": {
          "Effect": "スタミナ回復量[30%]増加",
          "RequiredLevel": 20,
          "RequiredSP": 2
        },
        "4": {
          "Effect": "スタミナ回復量[40%]増加",
          "RequiredLevel": 25,
          "RequiredSP": 2
        },
        "5": {
          "Effect": "スタミナ回復量[50%]増加",
          "RequiredLevel": 30,
          "RequiredSP": 3
        }
      }
    },
    "ImprovedBolt": {
      "Passive": true,
      "Name": "개량된 노리쇠",
      "ID": 1013,
      "RequireClass": {
        "CompareType": "atleast",
        "ClassIndex": 1
      },
      "Icon": "../assets/SkillIcons/Nabi/Icon_RoyarRifle_Skill_SGPassive2.png",
      "Levels": {
        "0": {
          "Description": "",
          "Effect": "",
          "RequiredLevel": 0,
          "RequiredSP": 0
        },
        "1": {
          "Effect": "패시브 효과: 기본공격 사용 시 5초동안 공격력이 35%만큼 증가합니다.(최대 3중첩)",
          "RequiredLevel": 57,
          "RequiredSP": 1
        },
        "2": {
          "Effect": "패시브 효과: 기본공격 사용 시 5초동안 공격력이 55%만큼 증가합니다.(최대 3중첩)",
          "RequiredLevel": 58,
          "RequiredSP": 1
        },
        "3": {
          "Effect": "패시브 효과: 기본공격 사용 시 5초동안 공격력이 75%만큼 증가합니다.(최대 3중첩)",
          "RequiredLevel": 59,
          "RequiredSP": 2
        }
      }
    },
    "ExtendedMagazine": {
      "Passive": true,
      "Name": "확장 탄창",
      "ID": 1011,
      "RowSpan": {
        "0": 2,
        "1": 1
      },
      "Icon": "../assets/SkillIcons/Nabi/Icon_RoyarRifle_Skill_SGPassive.png",
      "Levels": {
        "0": {
          "Description": "",
          "Effect": "",
          "RequiredLevel": 0,
          "RequiredSP": 0
        },
        "1": {
          "Effect": "SG 최대수치가 20만큼 증가합니다.",
          "RequiredLevel": 10,
          "RequiredSP": 1
        },
        "2": {
          "Effect": "SG 최대수치가 40만큼 증가합니다.",
          "RequiredLevel": 20,
          "RequiredSP": 1
        },
        "3": {
          "Effect": "SG 최대수치가 60만큼 증가합니다.",
          "RequiredLevel": 30,
          "RequiredSP": 2
        }
      }
    },
    "SightofLoyalty": {
      "Passive": true,
      "Name": "충심의 조준경",
      "DefaultLevel": 1,
      "ID": 1012,
      "RowSpan": {
        "0": 2,
        "1": 1
      },      
      "Icon": "../assets/SkillIcons/Common/Icon_Common_Skill_SoulMastery.png",
      "Levels": {
        "0": {
          "Description": "이나비의 특정 스킬들은 시전자의 공격으로 폭발하여 주변의 적들에게 피해를 주는 '폭심지'를 지면에 남깁니다. 폭심지는 10초 동안 유지됩니다.",
          "Effect": "",
          "RequiredLevel": 0,
          "RequiredSP": 0
        },
        "1": {
          "Effect": "[스킬 정보: 반동 역이용]\n지상 및 공중 기본공격의 소총 사격 후 아주 짧은 시간동안 스테미나 소모량이 30%만큼 감소합니다.\n\n*배틀룸에서는 반동 역이용 능력이 적용되지 않습니다.\n\n[스킬 정보: 폭발물 취급 훈련]\n폭심지 피해량: [300%]\n폭심지 슈퍼아머 파괴량: [450%]",
          "RequiredLevel": 0,
          "RequiredSP": 0
        }
      }
    },
    "TacticalAirStrike": {
      "Passive": true,
      "Name": "택티컬 에어스트라이크",
      "DefaultLevel": 1,
      "ID": 2003,
      "RequireClass": {
        "CompareType": "atleast",
        "ClassIndex": 1
      },
      "Icon": "../assets/SkillIcons/Nabi/Icon_RoyarRifle_Skill_TacticalAirStrike.png",
      "Assignable": false,
      "Levels": {
        "0": {
          "Description": "覚醒状態でのみスキル使用が可能です。\nスキル使用時に覚醒状態が解除されます。\n\n헬기를 소환한 후 지상으로 폭격을 가합니다.\n이나비가 다시 지상에 착륙한 후 강력한 다연장 미사일로 마무리합니다.",
          "Effect": "",
          "RequiredLevel": 0,
          "RequiredSP": 0,
          "Preview": {
            "Video": "../assets/SkillPreviews/Nabi/B_Skill_TacticalAirStrike.{{auto}}"
          }
        },
        "1": {
          "Effect": "피해량: [7250%]\n슈퍼아머 파괴량: [7250%]",
          "RequiredLevel": 57,
          "RequiredSP": 0
        }
      }
    },
    "Erosion": {
      "Passive": true,
      "Name": "イロージョン",
      "DefaultLevel": 1,
      "ID": 2001,
      "Icon": "../assets/SkillIcons/Nabi/Icon_RoyarRifle_Skill_BreakErode.png",
      "Assignable": false,
      "Levels": {
        "0": {
          "Description": "体を覚醒させ、身体能力を一時的に向上させる。\nソウルベイパーを消費し、スキルを使用する。",
          "Effect": "",
          "RequiredLevel": 0,
          "RequiredSP": 0,
          "Preview": {
            "Video": "../assets/SkillPreviews/Nabi/B_Skill_SoulViper_01.{{auto}}"
          }
        },
        "1": {
          "Effect": "1段階ゲージ消費（SV50消費）\n\n-방어도 관통이 5% 증가합니다.\n-치명타 확률이 5% 증가합니다.\n-이동속도가 20% 만큼 증가합니다.\n-SA状態になる。",
          "RequiredLevel": 0,
          "RequiredSP": 0
        }
      }
    },
    "Awakening": {
      "Passive": true,
      "Name": "覚醒",
      "DefaultLevel": 1,
      "ID": 2002,
      "RequireClass": {
        "CompareType": "atmost",
        "ClassIndex": 1
      },
      "Icon": "../assets/SkillIcons/Nabi/Icon_RoyarRifle_Skill_BreakWakeup.png",
      "Assignable": false,
      "Levels": {
        "0": {
          "Description": "体を覚醒させ、身体能力を一時的に向上させる。\nソウルベイパーを消費し、スキルを使用する。",
          "Effect": "",
          "RequiredLevel": 0,
          "RequiredSP": 0,
          "Preview": {
            "Video": "../assets/SkillPreviews/Nabi/B_Skill_SoulViper_02.{{auto}}"
          }
        },
        "1": {
          "Effect": "2段階ゲージ消費（SV100消費）\n\n60秒間、覚醒状態になる。\n-방어도 관통이 10% 증가합니다.\n-치명타 확률이 10% 증가합니다.\n-이동속도가 20% 만큼 증가합니다.\n-SA状態になる。",
          "RequiredLevel": 0,
          "RequiredSP": 0
        }
      }
    },
    "DesireAwakening": {
      "Passive": true,
      "Name": "デザイア覚醒",
      "DefaultLevel": 1,
      "ID": 2004,
      "RequireClass": {
        "CompareType": "atleast",
        "ClassIndex": 2
      },
      "Icon": "../assets/SkillIcons/Common/Icon_Common_Skill_DBreakErode.png",
      "Assignable": false,
      "Levels": {
        "0": {
          "Description": "体を覚醒させ、身体能力を一時的に向上させる。\nSV(ソウルベイパー)を消費し、スキルを使用する。",
          "Effect": "",
          "RequiredLevel": 0,
          "RequiredSP": 0,
          "Preview": {
            "Video": "../assets/SkillPreviews/Nabi/B_Skill_SoulViper_03.{{auto}}"
          }
        },
        "1": {
          "Effect": "2段階ゲージ消費（SV100消費）\n\n60秒間、デザイア覚醒状態になる。\n-与ダメージが20％上昇する。\n-SG消費量が20％減少する。\n-最大ダメージを固定する。\n-攻撃速度が20%増加する。\n-移動速度が30%増加する。\n-SA状態になる。\n-デザイアスキルが発動する。\n\n[デザイアスキル情報]\nExスキル使用後、効果が終了する。\n-60秒間スキルのダメージ量が1.3倍に上昇する。\n-라스트 스트라이크: 타격지점 가운데 적들에게 추가 타격을 입힙니다. \n-디스트로네일: 기둥이 남아있으며 지속시간동안 주변에 피해를 입힙니다.\n-택티컬 에어스트라이크: 마무리 미사일 타격이 강화 됩니다.",
          "RequiredLevel": 65,
          "RequiredSP": 0
        }
      }
    }
  }
}